{
  "lastUpdated": "2026-01-20",
  "summary": {
    "totalActions": 20,
    "totalLegalChallenges": 28,
    "blockedOrReversed": 4,
    "implementationRate": 0.5,
    "categorySummaries": [
      {
        "category": "immigration",
        "totalActions": 4,
        "blocked": 1,
        "implemented": 2,
        "pendingLitigation": 1,
        "legalChallenges": 6
      },
      {
        "category": "environment",
        "totalActions": 2,
        "blocked": 1,
        "implemented": 1,
        "pendingLitigation": 0,
        "legalChallenges": 3
      },
      {
        "category": "civil-rights",
        "totalActions": 2,
        "blocked": 1,
        "implemented": 0,
        "pendingLitigation": 1,
        "legalChallenges": 4
      },
      {
        "category": "government-reform",
        "totalActions": 3,
        "blocked": 0,
        "implemented": 1,
        "pendingLitigation": 1,
        "legalChallenges": 5
      },
      {
        "category": "economic-policy",
        "totalActions": 2,
        "blocked": 0,
        "implemented": 2,
        "pendingLitigation": 0,
        "legalChallenges": 2
      },
      {
        "category": "judiciary",
        "totalActions": 1,
        "blocked": 0,
        "implemented": 0,
        "pendingLitigation": 1,
        "legalChallenges": 1
      },
      {
        "category": "healthcare",
        "totalActions": 2,
        "blocked": 0,
        "implemented": 1,
        "pendingLitigation": 1,
        "legalChallenges": 3
      },
      {
        "category": "education",
        "totalActions": 1,
        "blocked": 1,
        "implemented": 0,
        "pendingLitigation": 0,
        "legalChallenges": 1
      },
      {
        "category": "foreign-policy",
        "totalActions": 2,
        "blocked": 0,
        "implemented": 2,
        "pendingLitigation": 0,
        "legalChallenges": 1
      },
      {
        "category": "media-press",
        "totalActions": 1,
        "blocked": 0,
        "implemented": 0,
        "pendingLitigation": 1,
        "legalChallenges": 2
      }
    ]
  },
  "actions": [
    {
      "id": "action-001",
      "title": "Executive Order on Securing the Southern Border and Resumption of Border Wall Construction",
      "type": "executive-order",
      "category": "immigration",
      "status": "partially-implemented",
      "description": "Directs the Department of Homeland Security to resume construction of the southern border wall, deploy additional Border Patrol agents, and reinstate the Remain in Mexico policy for asylum seekers. Declares a national emergency at the southern border to unlock military construction funding.",
      "dateIssued": "2025-01-20",
      "agencies": ["Department of Homeland Security", "Department of Defense", "U.S. Customs and Border Protection"],
      "pushbackIds": ["pushback-001", "pushback-002"],
      "relatedRiskCategories": ["security-apparatus", "fiscal-policy"],
      "sources": []
    },
    {
      "id": "action-002",
      "title": "Executive Order Ending Birthright Citizenship for Children of Undocumented Immigrants",
      "type": "executive-order",
      "category": "immigration",
      "status": "blocked",
      "description": "Attempts to reinterpret the 14th Amendment to deny automatic citizenship to children born in the United States to parents who are neither citizens nor lawful permanent residents. Directs federal agencies to cease issuing citizenship documents in such cases.",
      "dateIssued": "2025-01-20",
      "agencies": ["Department of State", "Social Security Administration", "Department of Homeland Security"],
      "pushbackIds": ["pushback-003", "pushback-004"],
      "relatedRiskCategories": ["civil-discourse", "judicial-independence"],
      "sources": []
    },
    {
      "id": "action-003",
      "title": "Presidential Memorandum on Interior Immigration Enforcement and Deportation Operations",
      "type": "presidential-memo",
      "category": "immigration",
      "status": "implemented",
      "description": "Directs ICE to expand interior enforcement operations, eliminate enforcement priorities that shielded certain classes of undocumented immigrants, and increases coordination with state and local law enforcement under 287(g) agreements.",
      "dateIssued": "2025-01-22",
      "agencies": ["Immigration and Customs Enforcement", "Department of Justice", "Department of Homeland Security"],
      "pushbackIds": ["pushback-005"],
      "relatedRiskCategories": ["security-apparatus", "civil-discourse"],
      "sources": []
    },
    {
      "id": "action-004",
      "title": "Proclamation Suspending Entry of Nationals from Designated Countries",
      "type": "proclamation",
      "category": "immigration",
      "status": "pending-litigation",
      "description": "Suspends entry into the United States of nationals from an expanded list of countries deemed to present elevated security risks. Expands the geographic scope beyond prior travel restriction orders to include additional African and Central Asian nations.",
      "dateIssued": "2025-02-03",
      "agencies": ["Department of State", "Department of Homeland Security", "National Security Council"],
      "pushbackIds": ["pushback-006"],
      "relatedRiskCategories": ["security-apparatus", "civil-discourse"],
      "sources": []
    },
    {
      "id": "action-005",
      "title": "Executive Order on Unleashing American Energy and Withdrawal from the Paris Climate Agreement",
      "type": "executive-order",
      "category": "environment",
      "status": "implemented",
      "description": "Withdraws the United States from the Paris Climate Agreement, reverses the moratorium on new federal oil and gas leasing, rescinds the prior administration's climate-related executive orders, and directs agencies to eliminate regulations that impede domestic energy production.",
      "dateIssued": "2025-01-20",
      "agencies": ["Environmental Protection Agency", "Department of the Interior", "Department of Energy"],
      "pushbackIds": ["pushback-007", "pushback-008"],
      "relatedRiskCategories": ["regulatory-stability", "trade-policy"],
      "sources": []
    },
    {
      "id": "action-006",
      "title": "Agency Rule Reversing EPA Vehicle Emissions Standards",
      "type": "agency-rule",
      "category": "environment",
      "status": "blocked",
      "description": "EPA finalizes a rule rolling back tailpipe emission standards for light-duty and medium-duty vehicles set under the prior administration. The revised rule significantly weakens targets for fleet-wide emissions reductions through 2032.",
      "dateIssued": "2025-06-15",
      "agencies": ["Environmental Protection Agency", "Department of Transportation"],
      "pushbackIds": ["pushback-009"],
      "relatedRiskCategories": ["regulatory-stability"],
      "sources": []
    },
    {
      "id": "action-007",
      "title": "Executive Order Eliminating Diversity, Equity, and Inclusion Programs in the Federal Government",
      "type": "executive-order",
      "category": "civil-rights",
      "status": "pending-litigation",
      "description": "Orders the termination of all DEI offices, programs, and initiatives across federal agencies. Prohibits federal contractors from maintaining DEI requirements and rescinds prior executive orders mandating affirmative action in federal contracting.",
      "dateIssued": "2025-01-21",
      "agencies": ["Office of Personnel Management", "Office of Management and Budget", "Equal Employment Opportunity Commission"],
      "pushbackIds": ["pushback-010", "pushback-011"],
      "relatedRiskCategories": ["institutional-independence", "civil-discourse"],
      "sources": []
    },
    {
      "id": "action-008",
      "title": "Policy Directive on Federal Recognition of Two Biological Sexes",
      "type": "policy-directive",
      "category": "civil-rights",
      "status": "blocked",
      "description": "Directs all federal agencies to define sex as exclusively male or female based on biology at birth for the purposes of federal law, regulations, and policy. Revokes prior guidance permitting gender identity-based accommodations in federal facilities and programs.",
      "dateIssued": "2025-01-20",
      "agencies": ["Department of Health and Human Services", "Department of Education", "Office of Personnel Management"],
      "pushbackIds": ["pushback-012", "pushback-013"],
      "relatedRiskCategories": ["civil-discourse", "judicial-independence"],
      "sources": []
    },
    {
      "id": "action-009",
      "title": "Executive Order Establishing the Department of Government Efficiency (DOGE)",
      "type": "executive-order",
      "category": "government-reform",
      "status": "partially-implemented",
      "description": "Creates the Department of Government Efficiency as a temporary advisory body within the Executive Office of the President, tasked with identifying waste, fraud, and inefficiency in federal spending. Grants DOGE access to agency financial systems and personnel records to conduct reviews.",
      "dateIssued": "2025-01-20",
      "agencies": ["Executive Office of the President", "Office of Management and Budget", "General Services Administration"],
      "pushbackIds": ["pushback-014", "pushback-015"],
      "relatedRiskCategories": ["institutional-independence", "government-contracts", "fiscal-policy"],
      "sources": []
    },
    {
      "id": "action-010",
      "title": "Presidential Memorandum on Federal Workforce Reduction and Hiring Freeze",
      "type": "presidential-memo",
      "category": "government-reform",
      "status": "implemented",
      "description": "Institutes a government-wide hiring freeze for civilian federal employees with limited exceptions for military and national security positions. Directs agencies to develop plans for reducing their workforce by 20% through attrition, voluntary separation incentives, and reductions in force.",
      "dateIssued": "2025-01-23",
      "agencies": ["Office of Personnel Management", "Office of Management and Budget"],
      "pushbackIds": ["pushback-016"],
      "relatedRiskCategories": ["institutional-independence", "government-contracts"],
      "sources": []
    },
    {
      "id": "action-011",
      "title": "Executive Order Reclassifying Federal Employees Under Schedule F",
      "type": "executive-order",
      "category": "government-reform",
      "status": "pending-litigation",
      "description": "Reinstates and expands Schedule F, reclassifying tens of thousands of career federal employees in policy-influencing positions as at-will employees who can be terminated without standard civil service protections.",
      "dateIssued": "2025-02-10",
      "agencies": ["Office of Personnel Management", "Office of Management and Budget", "Department of Justice"],
      "pushbackIds": ["pushback-017", "pushback-018"],
      "relatedRiskCategories": ["institutional-independence", "government-contracts"],
      "sources": []
    },
    {
      "id": "action-012",
      "title": "Executive Order Imposing Universal Baseline Tariffs on All Imports",
      "type": "executive-order",
      "category": "economic-policy",
      "status": "implemented",
      "description": "Imposes a baseline 10% tariff on all goods imported into the United States under the International Emergency Economic Powers Act, with additional reciprocal tariffs of up to 60% on goods from China and 25% on goods from Canada and Mexico.",
      "dateIssued": "2025-02-01",
      "agencies": ["U.S. Trade Representative", "Department of Commerce", "U.S. Customs and Border Protection"],
      "pushbackIds": ["pushback-019"],
      "relatedRiskCategories": ["trade-policy", "regulatory-stability", "fiscal-policy"],
      "sources": []
    },
    {
      "id": "action-013",
      "title": "Agency Rule on Cryptocurrency and Digital Asset Regulatory Framework",
      "type": "agency-rule",
      "category": "economic-policy",
      "status": "implemented",
      "description": "Establishes a new regulatory framework for digital assets classifying most cryptocurrencies as commodities rather than securities, transferring primary oversight from the SEC to the CFTC. Creates a favorable regulatory environment for domestic crypto exchanges and stablecoin issuers.",
      "dateIssued": "2025-04-20",
      "agencies": ["Securities and Exchange Commission", "Commodity Futures Trading Commission", "Department of the Treasury"],
      "pushbackIds": ["pushback-020"],
      "relatedRiskCategories": ["regulatory-stability", "fiscal-policy"],
      "sources": []
    },
    {
      "id": "action-014",
      "title": "Signing Statement on Judicial Appointments and Court Expansion Prevention Act",
      "type": "signing-statement",
      "category": "judiciary",
      "status": "pending-litigation",
      "description": "Signing statement accompanying legislation that reformed judicial nomination procedures. The statement asserts broad executive authority over the pace of judicial confirmations and challenges provisions requiring Senate consultation timelines as advisory rather than mandatory.",
      "dateIssued": "2025-07-12",
      "agencies": ["Department of Justice", "White House Counsel's Office"],
      "pushbackIds": ["pushback-021"],
      "relatedRiskCategories": ["judicial-independence", "institutional-independence"],
      "sources": []
    },
    {
      "id": "action-015",
      "title": "Executive Order on Healthcare Price Transparency and ACA Market Reforms",
      "type": "executive-order",
      "category": "healthcare",
      "status": "implemented",
      "description": "Expands healthcare price transparency requirements and directs HHS to approve state innovation waivers allowing alternatives to ACA marketplace plans. Permits the sale of short-term limited-duration insurance plans with coverage periods up to 36 months.",
      "dateIssued": "2025-03-15",
      "agencies": ["Department of Health and Human Services", "Centers for Medicare and Medicaid Services"],
      "pushbackIds": ["pushback-022"],
      "relatedRiskCategories": ["regulatory-stability"],
      "sources": []
    },
    {
      "id": "action-016",
      "title": "Agency Rule Restricting Mifepristone Distribution via Telemedicine",
      "type": "agency-rule",
      "category": "healthcare",
      "status": "pending-litigation",
      "description": "FDA finalizes rule reimposing the in-person dispensing requirement for mifepristone, prohibiting distribution by mail-order pharmacies and through telemedicine prescriptions. Adds new REMS (Risk Evaluation and Mitigation Strategy) requirements for prescribers.",
      "dateIssued": "2025-08-01",
      "agencies": ["Food and Drug Administration", "Department of Health and Human Services"],
      "pushbackIds": ["pushback-023", "pushback-024"],
      "relatedRiskCategories": ["regulatory-stability", "civil-discourse"],
      "sources": []
    },
    {
      "id": "action-017",
      "title": "Policy Directive Prohibiting Federal Funding for Schools with Gender-Identity Policies",
      "type": "policy-directive",
      "category": "education",
      "status": "blocked",
      "description": "Directs the Department of Education to withhold federal funding from school districts that maintain policies allowing transgender students to use facilities or participate in sports teams inconsistent with their biological sex at birth.",
      "dateIssued": "2025-05-10",
      "agencies": ["Department of Education", "Office for Civil Rights"],
      "pushbackIds": ["pushback-025"],
      "relatedRiskCategories": ["civil-discourse", "institutional-independence"],
      "sources": []
    },
    {
      "id": "action-018",
      "title": "Executive Order on Withdrawal from the World Health Organization",
      "type": "executive-order",
      "category": "foreign-policy",
      "status": "implemented",
      "description": "Initiates the formal process of withdrawing the United States from the World Health Organization, citing concerns over the organization's handling of international health emergencies and alleged undue influence by China. Redirects WHO funding to bilateral health aid programs.",
      "dateIssued": "2025-01-20",
      "agencies": ["Department of State", "Department of Health and Human Services"],
      "pushbackIds": ["pushback-026"],
      "relatedRiskCategories": ["institutional-independence", "trade-policy"],
      "sources": []
    },
    {
      "id": "action-019",
      "title": "Presidential Memorandum on Restructuring Foreign Aid and USAID Operations",
      "type": "presidential-memo",
      "category": "foreign-policy",
      "status": "implemented",
      "description": "Orders a 90-day freeze on all foreign aid disbursements pending a comprehensive review. Directs the consolidation of USAID functions into the State Department and the elimination of programs deemed inconsistent with the America First foreign policy doctrine.",
      "dateIssued": "2025-01-24",
      "agencies": ["Department of State", "U.S. Agency for International Development", "National Security Council"],
      "pushbackIds": [],
      "relatedRiskCategories": ["institutional-independence", "government-contracts"],
      "sources": []
    },
    {
      "id": "action-020",
      "title": "Executive Order on Preventing Federal Agencies from Censoring Lawful Speech Online",
      "type": "executive-order",
      "category": "media-press",
      "status": "pending-litigation",
      "description": "Prohibits federal agencies from communicating with social media companies to request or encourage the removal or suppression of lawful speech. Establishes a White House review board to investigate prior instances of government-directed content moderation and authorizes investigations into platforms alleged to have colluded with government censorship efforts.",
      "dateIssued": "2025-02-15",
      "agencies": ["Department of Justice", "Federal Trade Commission", "Federal Communications Commission"],
      "pushbackIds": ["pushback-027", "pushback-028"],
      "relatedRiskCategories": ["media-freedom", "civil-discourse", "institutional-independence"],
      "sources": []
    }
  ],
  "pushback": [
    {
      "id": "pushback-001",
      "title": "ACLU v. Department of Homeland Security - Border Wall Emergency Declaration Challenge",
      "type": "federal-lawsuit",
      "caseStatus": "appealed",
      "description": "The ACLU challenges the emergency declaration used to redirect military construction funds for border wall construction, arguing it exceeds executive authority and violates the Appropriations Clause of the Constitution.",
      "dateFiled": "2025-02-05",
      "court": "U.S. District Court for the District of Columbia",
      "plaintiffs": ["American Civil Liberties Union", "Sierra Club", "Southern Border Communities Coalition"],
      "actionIds": ["action-001"],
      "outcome": "District court issued preliminary injunction blocking fund diversion; administration appealed to D.C. Circuit.",
      "sources": []
    },
    {
      "id": "pushback-002",
      "title": "State of California v. DHS - Remain in Mexico Policy Reinstatement",
      "type": "state-lawsuit",
      "caseStatus": "preliminary-injunction",
      "description": "California and a coalition of states challenge the reinstatement of the Remain in Mexico policy, arguing it violates the Administrative Procedure Act and international asylum obligations.",
      "dateFiled": "2025-03-10",
      "court": "U.S. District Court for the Northern District of California",
      "plaintiffs": ["State of California", "State of Washington", "State of Oregon", "State of Illinois"],
      "actionIds": ["action-001"],
      "outcome": "Preliminary injunction pending; hearing scheduled.",
      "sources": []
    },
    {
      "id": "pushback-003",
      "title": "State of New Jersey v. United States - Birthright Citizenship Executive Order Challenge",
      "type": "state-lawsuit",
      "caseStatus": "injunction-granted",
      "description": "A coalition of 22 states files suit challenging the birthright citizenship executive order as a direct violation of the 14th Amendment's Citizenship Clause, arguing the executive cannot unilaterally reinterpret a constitutional provision.",
      "dateFiled": "2025-01-21",
      "court": "U.S. District Court for the Western District of Washington",
      "plaintiffs": ["State of New Jersey", "State of California", "State of New York", "State of Massachusetts"],
      "actionIds": ["action-002"],
      "outcome": "Federal judge granted nationwide temporary restraining order, later converted to preliminary injunction, finding the order plainly unconstitutional.",
      "sources": []
    },
    {
      "id": "pushback-004",
      "title": "CASA de Maryland v. Trump - Birthright Citizenship Constitutional Challenge",
      "type": "federal-lawsuit",
      "caseStatus": "injunction-granted",
      "description": "Immigrant advocacy organizations challenge the birthright citizenship order on behalf of expectant mothers and families, arguing the order violates the 14th Amendment and the equal protection clause.",
      "dateFiled": "2025-01-23",
      "court": "U.S. District Court for the District of Maryland",
      "plaintiffs": ["CASA de Maryland", "National Immigration Law Center", "Asylum Seeker Advocacy Project"],
      "actionIds": ["action-002"],
      "outcome": "Court granted preliminary injunction blocking enforcement of the order.",
      "sources": []
    },
    {
      "id": "pushback-005",
      "title": "City of Chicago v. ICE - Sanctuary City Enforcement Operations Challenge",
      "type": "federal-lawsuit",
      "caseStatus": "filed",
      "description": "Chicago and other sanctuary cities sue to block expanded ICE enforcement operations in sensitive locations, arguing the operations violate Fourth Amendment protections and longstanding enforcement guidelines.",
      "dateFiled": "2025-04-15",
      "court": "U.S. District Court for the Northern District of Illinois",
      "plaintiffs": ["City of Chicago", "City of Denver", "City of Los Angeles", "City of New York"],
      "actionIds": ["action-003"],
      "sources": []
    },
    {
      "id": "pushback-006",
      "title": "Muslim Advocates v. Trump - Expanded Travel Restriction Challenge",
      "type": "federal-lawsuit",
      "caseStatus": "preliminary-injunction",
      "description": "Civil rights organizations challenge the expanded travel ban as exceeding statutory authority under the Immigration and Nationality Act and as discriminatory toward Muslim-majority countries in violation of the Establishment Clause.",
      "dateFiled": "2025-02-20",
      "court": "U.S. District Court for the Eastern District of Virginia",
      "plaintiffs": ["Muslim Advocates", "International Refugee Assistance Project", "National Immigration Project of the National Lawyers Guild"],
      "actionIds": ["action-004"],
      "sources": []
    },
    {
      "id": "pushback-007",
      "title": "State of New York v. EPA - Paris Agreement Withdrawal and Emissions Rollback",
      "type": "state-lawsuit",
      "caseStatus": "filed",
      "description": "A coalition of states challenges the rescission of climate regulations, arguing that the EPA has a statutory obligation under the Clean Air Act to regulate greenhouse gas emissions regardless of the Paris Agreement withdrawal.",
      "dateFiled": "2025-03-01",
      "court": "U.S. Court of Appeals for the D.C. Circuit",
      "plaintiffs": ["State of New York", "State of California", "State of Connecticut", "State of Vermont"],
      "actionIds": ["action-005"],
      "sources": []
    },
    {
      "id": "pushback-008",
      "title": "Earthjustice v. Department of the Interior - Federal Lands Leasing Challenge",
      "type": "federal-lawsuit",
      "caseStatus": "filed",
      "description": "Environmental organizations challenge the resumption of federal oil and gas leasing on public lands, arguing the leasing decisions were made without the environmental review required by the National Environmental Policy Act.",
      "dateFiled": "2025-04-01",
      "court": "U.S. District Court for the District of Montana",
      "plaintiffs": ["Earthjustice", "Sierra Club", "Wilderness Society", "Center for Biological Diversity"],
      "actionIds": ["action-005"],
      "sources": []
    },
    {
      "id": "pushback-009",
      "title": "California Air Resources Board v. EPA - Vehicle Emissions Standards Challenge",
      "type": "state-lawsuit",
      "caseStatus": "injunction-granted",
      "description": "California and states that follow its emissions standards challenge the rollback of vehicle emissions rules, arguing the EPA failed to provide adequate scientific justification and violated the Clean Air Act's waiver provisions.",
      "dateFiled": "2025-07-20",
      "court": "U.S. Court of Appeals for the D.C. Circuit",
      "plaintiffs": ["California Air Resources Board", "State of New York", "State of Massachusetts", "State of Oregon"],
      "actionIds": ["action-006"],
      "outcome": "D.C. Circuit granted administrative stay pending full review, effectively blocking the rule.",
      "sources": []
    },
    {
      "id": "pushback-010",
      "title": "National Association for the Advancement of Colored People v. OPM - DEI Elimination Challenge",
      "type": "federal-lawsuit",
      "caseStatus": "preliminary-injunction",
      "description": "The NAACP and other civil rights organizations challenge the elimination of DEI programs, arguing the executive order violates the First Amendment rights of federal employees and exceeds executive authority by preempting congressionally mandated equal opportunity programs.",
      "dateFiled": "2025-02-10",
      "court": "U.S. District Court for the District of Columbia",
      "plaintiffs": ["NAACP", "National Urban League", "Leadership Conference on Civil and Human Rights"],
      "actionIds": ["action-007"],
      "sources": []
    },
    {
      "id": "pushback-011",
      "title": "Federal Employee Unions Coalition v. United States - DEI and Workforce Rights Challenge",
      "type": "federal-lawsuit",
      "caseStatus": "filed",
      "description": "A coalition of federal employee unions challenges the DEI order and associated personnel actions, arguing they violate Title VII of the Civil Rights Act and the due process rights of employees whose positions were eliminated.",
      "dateFiled": "2025-03-05",
      "court": "U.S. District Court for the District of Columbia",
      "plaintiffs": ["American Federation of Government Employees", "National Treasury Employees Union", "National Federation of Federal Employees"],
      "actionIds": ["action-007"],
      "sources": []
    },
    {
      "id": "pushback-012",
      "title": "Lambda Legal v. HHS - Biological Sex Policy Directive Challenge",
      "type": "federal-lawsuit",
      "caseStatus": "injunction-granted",
      "description": "LGBTQ rights organizations challenge the sex-definition policy directive, arguing it violates the Supreme Court's Bostock v. Clayton County ruling that Title VII protects against discrimination based on gender identity and sexual orientation.",
      "dateFiled": "2025-02-15",
      "court": "U.S. District Court for the District of Maryland",
      "plaintiffs": ["Lambda Legal", "ACLU", "National Center for Transgender Equality"],
      "actionIds": ["action-008"],
      "outcome": "Court issued preliminary injunction blocking enforcement as applied to federal employment and healthcare programs.",
      "sources": []
    },
    {
      "id": "pushback-013",
      "title": "State of Washington v. Department of Education - Sex Definition in Schools Challenge",
      "type": "state-lawsuit",
      "caseStatus": "ruling-against",
      "description": "Washington and other states challenge the application of the sex-definition directive to schools receiving federal funds, arguing it conflicts with Title IX and established judicial precedent protecting transgender students.",
      "dateFiled": "2025-03-20",
      "court": "U.S. District Court for the Western District of Washington",
      "plaintiffs": ["State of Washington", "State of Oregon", "State of Colorado", "State of Minnesota"],
      "actionIds": ["action-008"],
      "outcome": "Court ruled the directive as applied to educational settings is unlawful; administration appealing to the Ninth Circuit.",
      "sources": []
    },
    {
      "id": "pushback-014",
      "title": "National Treasury Employees Union v. Executive Office of the President - DOGE Access to Federal Systems",
      "type": "federal-lawsuit",
      "caseStatus": "injunction-granted",
      "description": "Federal employee unions challenge DOGE's access to sensitive agency personnel and financial systems, arguing that DOGE personnel lack security clearances and that the access violates the Privacy Act and the Federal Information Security Management Act.",
      "dateFiled": "2025-02-08",
      "court": "U.S. District Court for the District of Columbia",
      "plaintiffs": ["National Treasury Employees Union", "American Federation of Government Employees"],
      "actionIds": ["action-009"],
      "outcome": "Court issued temporary restraining order limiting DOGE access to systems containing personally identifiable information.",
      "sources": []
    },
    {
      "id": "pushback-015",
      "title": "Senate Democratic Caucus Resolution Challenging DOGE Constitutional Authority",
      "type": "congressional-action",
      "caseStatus": "filed",
      "description": "Senate Democrats introduce a resolution declaring that DOGE's operations exceed the scope of executive authority by effectively exercising legislative power of the purse. The resolution calls for GAO investigation into DOGE's activities and their compliance with the Antideficiency Act.",
      "dateFiled": "2025-03-15",
      "plaintiffs": ["Senate Democratic Caucus", "Senate Committee on Homeland Security and Governmental Affairs (Minority)"],
      "actionIds": ["action-009"],
      "sources": []
    },
    {
      "id": "pushback-016",
      "title": "American Federation of Government Employees v. OPM - Federal Hiring Freeze Challenge",
      "type": "federal-lawsuit",
      "caseStatus": "dismissed",
      "description": "Federal employee unions challenge the government-wide hiring freeze and workforce reduction plans, arguing they violate civil service protections and that workforce reduction targets are arbitrary and capricious under the APA.",
      "dateFiled": "2025-02-20",
      "court": "U.S. District Court for the District of Columbia",
      "plaintiffs": ["American Federation of Government Employees", "National Federation of Federal Employees"],
      "actionIds": ["action-010"],
      "outcome": "Court dismissed the case, ruling that the President has broad authority over federal workforce management and the hiring freeze falls within executive discretion.",
      "sources": []
    },
    {
      "id": "pushback-017",
      "title": "National Treasury Employees Union v. United States - Schedule F Reclassification Challenge",
      "type": "federal-lawsuit",
      "caseStatus": "preliminary-injunction",
      "description": "Federal employee unions and good-government organizations challenge Schedule F, arguing it violates the Civil Service Reform Act and the merit system principles by converting career civil servants to at-will employees subject to political termination.",
      "dateFiled": "2025-03-01",
      "court": "U.S. District Court for the District of Columbia",
      "plaintiffs": ["National Treasury Employees Union", "American Federation of Government Employees", "Public Employees for Environmental Responsibility"],
      "actionIds": ["action-011"],
      "sources": []
    },
    {
      "id": "pushback-018",
      "title": "State Attorneys General Coalition v. OPM - Schedule F Federalism Challenge",
      "type": "state-lawsuit",
      "caseStatus": "filed",
      "description": "A coalition of state attorneys general files suit arguing that Schedule F reclassifications of employees in grant-making and regulatory positions will disrupt cooperative federalism programs and violate the Spending Clause.",
      "dateFiled": "2025-04-10",
      "court": "U.S. District Court for the Northern District of California",
      "plaintiffs": ["State of California", "State of New York", "State of Illinois", "State of New Mexico"],
      "actionIds": ["action-011"],
      "sources": []
    },
    {
      "id": "pushback-019",
      "title": "National Foreign Trade Council v. United States - Universal Tariff Authority Challenge",
      "type": "federal-lawsuit",
      "caseStatus": "appealed",
      "description": "Industry groups challenge the use of IEEPA to impose universal tariffs, arguing the statute was not intended to authorize broad-based trade measures and that the tariffs effectively constitute a tax increase requiring congressional authorization.",
      "dateFiled": "2025-03-15",
      "court": "U.S. Court of International Trade",
      "plaintiffs": ["National Foreign Trade Council", "U.S. Chamber of Commerce", "National Retail Federation"],
      "actionIds": ["action-012"],
      "outcome": "Court of International Trade upheld the tariffs; case appealed to the Federal Circuit.",
      "sources": []
    },
    {
      "id": "pushback-020",
      "title": "Securities Industry and Financial Markets Association v. SEC - Crypto Regulatory Framework Challenge",
      "type": "federal-lawsuit",
      "caseStatus": "filed",
      "description": "Securities industry groups challenge the transfer of crypto oversight from SEC to CFTC, arguing the reclassification of digital assets as commodities was done without proper APA notice-and-comment rulemaking and conflicts with existing securities law precedent.",
      "dateFiled": "2025-06-01",
      "court": "U.S. District Court for the Southern District of New York",
      "plaintiffs": ["Securities Industry and Financial Markets Association", "Investment Company Institute"],
      "actionIds": ["action-013"],
      "sources": []
    },
    {
      "id": "pushback-021",
      "title": "Senate Judiciary Committee Challenge to Judicial Appointments Signing Statement",
      "type": "congressional-action",
      "caseStatus": "filed",
      "description": "The Senate Judiciary Committee minority issues a formal challenge to the signing statement, arguing the President cannot unilaterally declare Senate consultation requirements to be advisory. Introduces legislation to codify mandatory consultation timelines.",
      "dateFiled": "2025-07-25",
      "plaintiffs": ["Senate Judiciary Committee (Minority Members)", "Senate Democratic Leadership"],
      "actionIds": ["action-014"],
      "sources": []
    },
    {
      "id": "pushback-022",
      "title": "American Medical Association v. HHS - Short-Term Insurance Plan Expansion Challenge",
      "type": "federal-lawsuit",
      "caseStatus": "filed",
      "description": "Healthcare provider organizations challenge the expansion of short-term limited-duration insurance plans, arguing they undermine ACA risk pools, lack essential health benefit requirements, and that HHS exceeded its authority in approving overly broad state waivers.",
      "dateFiled": "2025-05-20",
      "court": "U.S. District Court for the District of Columbia",
      "plaintiffs": ["American Medical Association", "American Hospital Association", "American Cancer Society Cancer Action Network"],
      "actionIds": ["action-015"],
      "sources": []
    },
    {
      "id": "pushback-023",
      "title": "American College of Obstetricians and Gynecologists v. FDA - Mifepristone Access Challenge",
      "type": "federal-lawsuit",
      "caseStatus": "preliminary-injunction",
      "description": "Medical professional organizations challenge the reimposition of in-person dispensing requirements for mifepristone, arguing the FDA ignored its own scientific findings on the drug's safety and acted arbitrarily in reversing its prior determination.",
      "dateFiled": "2025-09-01",
      "court": "U.S. District Court for the Eastern District of Washington",
      "plaintiffs": ["American College of Obstetricians and Gynecologists", "Society for Maternal-Fetal Medicine"],
      "actionIds": ["action-016"],
      "sources": []
    },
    {
      "id": "pushback-024",
      "title": "State of Oregon v. FDA - Mifepristone Telemedicine Restriction",
      "type": "state-lawsuit",
      "caseStatus": "preliminary-injunction",
      "description": "A coalition of states challenges the mifepristone rule, arguing it is preempted by state pharmacy laws and that the FDA failed to provide adequate justification for reversing the telemedicine dispensing authorization in violation of the APA.",
      "dateFiled": "2025-09-15",
      "court": "U.S. District Court for the District of Oregon",
      "plaintiffs": ["State of Oregon", "State of Washington", "State of California", "State of New York", "State of Massachusetts"],
      "actionIds": ["action-016"],
      "sources": []
    },
    {
      "id": "pushback-025",
      "title": "GLSEN v. Department of Education - Federal Funding Withholding Challenge",
      "type": "federal-lawsuit",
      "caseStatus": "injunction-granted",
      "description": "Education advocacy organizations and affected school districts challenge the withholding of federal funds, arguing the Department of Education lacks statutory authority to impose conditions on funding not established by Congress and that the directive violates the Spending Clause.",
      "dateFiled": "2025-06-15",
      "court": "U.S. District Court for the District of Columbia",
      "plaintiffs": ["GLSEN", "National Education Association", "School District of Philadelphia"],
      "actionIds": ["action-017"],
      "outcome": "Court granted preliminary injunction blocking the funding withholding, finding the Department exceeded its statutory authority.",
      "sources": []
    },
    {
      "id": "pushback-026",
      "title": "Global Health Advocates v. Department of State - WHO Withdrawal Challenge",
      "type": "federal-lawsuit",
      "caseStatus": "dismissed",
      "description": "Public health organizations challenge the WHO withdrawal, arguing that the withdrawal requires congressional authorization because it effectively abrogates a treaty ratified by the Senate. Seeks to block the redirection of WHO funding.",
      "dateFiled": "2025-04-01",
      "court": "U.S. District Court for the District of Columbia",
      "plaintiffs": ["Global Health Council", "Partners in Health", "Doctors Without Borders USA"],
      "actionIds": ["action-018"],
      "outcome": "Court dismissed the case for lack of standing, finding the plaintiff organizations did not demonstrate concrete and particularized injury.",
      "sources": []
    },
    {
      "id": "pushback-027",
      "title": "Center for Democracy and Technology v. White House - Speech Review Board Challenge",
      "type": "federal-lawsuit",
      "caseStatus": "preliminary-injunction",
      "description": "Digital rights organizations challenge the establishment of the White House review board investigating content moderation partnerships, arguing it constitutes government retaliation against protected speech and creates a chilling effect on private platforms' editorial discretion.",
      "dateFiled": "2025-04-01",
      "court": "U.S. District Court for the Northern District of California",
      "plaintiffs": ["Center for Democracy and Technology", "Electronic Frontier Foundation", "Knight First Amendment Institute"],
      "actionIds": ["action-020"],
      "sources": []
    },
    {
      "id": "pushback-028",
      "title": "Meta Platforms and Alphabet v. FTC - Platform Investigation Challenge",
      "type": "federal-lawsuit",
      "caseStatus": "filed",
      "description": "Major technology companies challenge the FTC's authority to investigate prior content moderation decisions, arguing the investigations exceed the FTC's statutory mandate and violate the companies' First Amendment editorial rights.",
      "dateFiled": "2025-06-10",
      "court": "U.S. District Court for the Northern District of California",
      "plaintiffs": ["Meta Platforms Inc.", "Alphabet Inc."],
      "actionIds": ["action-020"],
      "sources": []
    }
  ]
}